zibai/__init__.py
zibai/__main__.py
zibai/cli.py
zibai/const.py
zibai/core.py
zibai/h11.py
zibai/logger.py
zibai/middlewares/__init__.py
zibai/middlewares/limit_request_count.py
zibai/multiprocess.py
zibai/reloader.py
zibai/utils.py
zibai/wsgi_typing.py
zibai_server-0.13.0.dist-info/METADATA
zibai_server-0.13.0.dist-info/WHEEL
zibai_server-0.13.0.dist-info/entry_points.txt
zibai_server-0.13.0.dist-info/licenses/LICENCE
zibai_server-0.13.0.dist-info/RECORD
