Metadata-Version: 2.1
Name: zibai-server
Version: 0.13.0
Summary: A modern high-performance Python WSGI server.
Author-Email: abersheeran <me@abersheeran.com>
License: Apache-2.0
Project-URL: repository, https://github.com/abersheeran/zibai
Requires-Python: >=3.10
Requires-Dist: h11>=0.14.0
Provides-Extra: gevent
Requires-Dist: gevent>=23.9.1; extra == "gevent"
Provides-Extra: reload
Requires-Dist: watchdog>=3.0.0; extra == "reload"
